fastframework/__init__.py
fastframework/__main__.py
fastframework/app.py
fastframework/defaults.py
fastframework/models.py
fastframework/modules.py
fastframework/config/__init__.py
fastframework/config/loader.py
fastframework/config/validator.py
fastframework-0.3.dist-info/LICENSE
fastframework-0.3.dist-info/METADATA
fastframework-0.3.dist-info/WHEEL
fastframework-0.3.dist-info/top_level.txt
fastframework-0.3.dist-info/RECORD
