Metadata-Version: 2.1
Name: fastframework
Version: 0.3
Summary: A fastapi - sqlalchemy based framework
Home-page: https://github.com/divad1196/fastwork
Author: Gallay David
Author-email: davidtennis96@hotmail.com
License: UNKNOWN
Platform: UNKNOWN
Classifier: Programming Language :: Python :: 3
Classifier: License :: OSI Approved :: MIT License
Classifier: Operating System :: OS Independent
